CONTRIBUTING.md
LICENSE
MANIFEST.in
README.md
settings.ini
setup.py
textprobe/__init__.py
textprobe/_nbdev.py
textprobe/core.py
textprobe.egg-info/PKG-INFO
textprobe.egg-info/SOURCES.txt
textprobe.egg-info/dependency_links.txt
textprobe.egg-info/entry_points.txt
textprobe.egg-info/not-zip-safe
textprobe.egg-info/top_level.txt