Metadata-Version: 2.1
Name: textprobe
Version: 0.0.2
Summary: nlp tool
Home-page: UNKNOWN
Author: TextProbe
Author-email: textprobe.com@gmail.com
License: Apache Software License 2.0
Keywords: nlp
Platform: UNKNOWN
Classifier: Development Status :: 3 - Alpha
Classifier: Intended Audience :: Developers
Classifier: Natural Language :: English
Classifier: Programming Language :: Python :: 3.6
Classifier: Programming Language :: Python :: 3.7
Classifier: Programming Language :: Python :: 3.8
Classifier: License :: OSI Approved :: Apache Software License
Requires-Python: >=3.6
